{"verses":[{"id":3083,"verse_number":151,"verse_key":"26:151","hizb_number":38,"rub_el_hizb_number":149,"ruku_number":323,"manzil_number":5,"sajdah_number":null,"page_number":373,"juz_number":19,"words":[{"id":80627,"position":1,"audio_url":"wbw/026_151_001.mp3","verse_key":"26:151","verse_id":3083,"location":"26:151:1","text_uthmani":"وَلَا","qpc_uthmani_hafs":"وَلَا","char_type_name":"word","page_number":373,"line_number":9,"text":"وَلَا","translation":{"text":"And (do) not","language_name":"english","language_id":38},"transliteration":{"text":"walā","language_name":"english","language_id":38}},{"id":80628,"position":2,"audio_url":"wbw/026_151_002.mp3","verse_key":"26:151","verse_id":3083,"location":"26:151:2","text_uthmani":"تُطِيعُوٓا۟","qpc_uthmani_hafs":"تُطِيعُوٓاْ","char_type_name":"word","page_number":373,"line_number":9,"text":"تُطِيعُوٓاْ","translation":{"text":"obey","language_name":"english","language_id":38},"transliteration":{"text":"tuṭīʿū","language_name":"english","language_id":38}},{"id":80629,"position":3,"audio_url":"wbw/026_151_003.mp3","verse_key":"26:151","verse_id":3083,"location":"26:151:3","text_uthmani":"أَمْرَ","qpc_uthmani_hafs":"أَمۡرَ","char_type_name":"word","page_number":373,"line_number":9,"text":"أَمۡرَ","translation":{"text":"(the) command","language_name":"english","language_id":38},"transliteration":{"text":"amra","language_name":"english","language_id":38}},{"id":80630,"position":4,"audio_url":"wbw/026_151_004.mp3","verse_key":"26:151","verse_id":3083,"location":"26:151:4","text_uthmani":"ٱلْمُسْرِفِينَ","qpc_uthmani_hafs":"ٱلۡمُسۡرِفِينَ","char_type_name":"word","page_number":373,"line_number":9,"text":"ٱلۡمُسۡرِفِينَ","translation":{"text":"(of) the transgressors","language_name":"english","language_id":38},"transliteration":{"text":"l-mus'rifīna","language_name":"english","language_id":38}},{"id":80631,"position":5,"audio_url":null,"verse_key":"26:151","verse_id":3083,"location":"26:151:5","text_uthmani":"١٥١","qpc_uthmani_hafs":"١٥١","char_type_name":"end","page_number":373,"line_number":9,"text":"١٥١","translation":{"text":"(151)","language_name":"english","language_id":38},"transliteration":{"text":null,"language_name":"english","language_id":38}}]},{"id":3084,"verse_number":152,"verse_key":"26:152","hizb_number":38,"rub_el_hizb_number":149,"ruku_number":323,"manzil_number":5,"sajdah_number":null,"page_number":373,"juz_number":19,"words":[{"id":80632,"position":1,"audio_url":"wbw/026_152_001.mp3","verse_key":"26:152","verse_id":3084,"location":"26:152:1","text_uthmani":"ٱلَّذِينَ","qpc_uthmani_hafs":"ٱلَّذِينَ","char_type_name":"word","page_number":373,"line_number":9,"text":"ٱلَّذِينَ","translation":{"text":"Those who","language_name":"english","language_id":38},"transliteration":{"text":"alladhīna","language_name":"english","language_id":38}},{"id":80633,"position":2,"audio_url":"wbw/026_152_002.mp3","verse_key":"26:152","verse_id":3084,"location":"26:152:2","text_uthmani":"يُفْسِدُونَ","qpc_uthmani_hafs":"يُفۡسِدُونَ","char_type_name":"word","page_number":373,"line_number":9,"text":"يُفۡسِدُونَ","translation":{"text":"spread corruption","language_name":"english","language_id":38},"transliteration":{"text":"yuf'sidūna","language_name":"english","language_id":38}},{"id":80634,"position":3,"audio_url":"wbw/026_152_003.mp3","verse_key":"26:152","verse_id":3084,"location":"26:152:3","text_uthmani":"فِى","qpc_uthmani_hafs":"فِي","char_type_name":"word","page_number":373,"line_number":9,"text":"فِي","translation":{"text":"in","language_name":"english","language_id":38},"transliteration":{"text":"fī","language_name":"english","language_id":38}},{"id":80635,"position":4,"audio_url":"wbw/026_152_004.mp3","verse_key":"26:152","verse_id":3084,"location":"26:152:4","text_uthmani":"ٱلْأَرْضِ","qpc_uthmani_hafs":"ٱلۡأَرۡضِ","char_type_name":"word","page_number":373,"line_number":9,"text":"ٱلۡأَرۡضِ","translation":{"text":"the earth","language_name":"english","language_id":38},"transliteration":{"text":"l-arḍi","language_name":"english","language_id":38}},{"id":80636,"position":5,"audio_url":"wbw/026_152_005.mp3","verse_key":"26:152","verse_id":3084,"location":"26:152:5","text_uthmani":"وَلَا","qpc_uthmani_hafs":"وَلَا","char_type_name":"word","page_number":373,"line_number":10,"text":"وَلَا","translation":{"text":"and (do) not","language_name":"english","language_id":38},"transliteration":{"text":"walā","language_name":"english","language_id":38}},{"id":80637,"position":6,"audio_url":"wbw/026_152_006.mp3","verse_key":"26:152","verse_id":3084,"location":"26:152:6","text_uthmani":"يُصْلِحُونَ","qpc_uthmani_hafs":"يُصۡلِحُونَ","char_type_name":"word","page_number":373,"line_number":10,"text":"يُصۡلِحُونَ","translation":{"text":"reform","language_name":"english","language_id":38},"transliteration":{"text":"yuṣ'liḥūna","language_name":"english","language_id":38}},{"id":80638,"position":7,"audio_url":null,"verse_key":"26:152","verse_id":3084,"location":"26:152:7","text_uthmani":"١٥٢","qpc_uthmani_hafs":"١٥٢","char_type_name":"end","page_number":373,"line_number":10,"text":"١٥٢","translation":{"text":"(152)","language_name":"english","language_id":38},"transliteration":{"text":null,"language_name":"english","language_id":38}}]},{"id":3085,"verse_number":153,"verse_key":"26:153","hizb_number":38,"rub_el_hizb_number":149,"ruku_number":323,"manzil_number":5,"sajdah_number":null,"page_number":373,"juz_number":19,"words":[{"id":80809,"position":1,"audio_url":"wbw/026_153_001.mp3","verse_key":"26:153","verse_id":3085,"location":"26:153:1","text_uthmani":"قَالُوٓا۟","qpc_uthmani_hafs":"قَالُوٓاْ","char_type_name":"word","page_number":373,"line_number":10,"text":"قَالُوٓاْ","translation":{"text":"They said","language_name":"english","language_id":38},"transliteration":{"text":"qālū","language_name":"english","language_id":38}},{"id":80810,"position":2,"audio_url":"wbw/026_153_002.mp3","verse_key":"26:153","verse_id":3085,"location":"26:153:2","text_uthmani":"إِنَّمَآ","qpc_uthmani_hafs":"إِنَّمَآ","char_type_name":"word","page_number":373,"line_number":10,"text":"إِنَّمَآ","translation":{"text":"Only","language_name":"english","language_id":38},"transliteration":{"text":"innamā","language_name":"english","language_id":38}},{"id":80811,"position":3,"audio_url":"wbw/026_153_003.mp3","verse_key":"26:153","verse_id":3085,"location":"26:153:3","text_uthmani":"أَنتَ","qpc_uthmani_hafs":"أَنتَ","char_type_name":"word","page_number":373,"line_number":10,"text":"أَنتَ","translation":{"text":"you","language_name":"english","language_id":38},"transliteration":{"text":"anta","language_name":"english","language_id":38}},{"id":80812,"position":4,"audio_url":"wbw/026_153_004.mp3","verse_key":"26:153","verse_id":3085,"location":"26:153:4","text_uthmani":"مِنَ","qpc_uthmani_hafs":"مِنَ","char_type_name":"word","page_number":373,"line_number":10,"text":"مِنَ","translation":{"text":"(are) of","language_name":"english","language_id":38},"transliteration":{"text":"mina","language_name":"english","language_id":38}},{"id":80813,"position":5,"audio_url":"wbw/026_153_005.mp3","verse_key":"26:153","verse_id":3085,"location":"26:153:5","text_uthmani":"ٱلْمُسَحَّرِينَ","qpc_uthmani_hafs":"ٱلۡمُسَحَّرِينَ","char_type_name":"word","page_number":373,"line_number":10,"text":"ٱلۡمُسَحَّرِينَ","translation":{"text":"those bewitched","language_name":"english","language_id":38},"transliteration":{"text":"l-musaḥarīna","language_name":"english","language_id":38}},{"id":80814,"position":6,"audio_url":null,"verse_key":"26:153","verse_id":3085,"location":"26:153:6","text_uthmani":"١٥٣","qpc_uthmani_hafs":"١٥٣","char_type_name":"end","page_number":373,"line_number":10,"text":"١٥٣","translation":{"text":"(153)","language_name":"english","language_id":38},"transliteration":{"text":null,"language_name":"english","language_id":38}}]},{"id":3086,"verse_number":154,"verse_key":"26:154","hizb_number":38,"rub_el_hizb_number":149,"ruku_number":323,"manzil_number":5,"sajdah_number":null,"page_number":373,"juz_number":19,"words":[{"id":80919,"position":1,"audio_url":"wbw/026_154_001.mp3","verse_key":"26:154","verse_id":3086,"location":"26:154:1","text_uthmani":"مَآ","qpc_uthmani_hafs":"مَآ","char_type_name":"word","page_number":373,"line_number":10,"text":"مَآ","translation":{"text":"Not","language_name":"english","language_id":38},"transliteration":{"text":"mā","language_name":"english","language_id":38}},{"id":80920,"position":2,"audio_url":"wbw/026_154_002.mp3","verse_key":"26:154","verse_id":3086,"location":"26:154:2","text_uthmani":"أَنتَ","qpc_uthmani_hafs":"أَنتَ","char_type_name":"word","page_number":373,"line_number":10,"text":"أَنتَ","translation":{"text":"you","language_name":"english","language_id":38},"transliteration":{"text":"anta","language_name":"english","language_id":38}},{"id":80921,"position":3,"audio_url":"wbw/026_154_003.mp3","verse_key":"26:154","verse_id":3086,"location":"26:154:3","text_uthmani":"إِلَّا","qpc_uthmani_hafs":"إِلَّا","char_type_name":"word","page_number":373,"line_number":11,"text":"إِلَّا","translation":{"text":"(are) except","language_name":"english","language_id":38},"transliteration":{"text":"illā","language_name":"english","language_id":38}},{"id":80922,"position":4,"audio_url":"wbw/026_154_004.mp3","verse_key":"26:154","verse_id":3086,"location":"26:154:4","text_uthmani":"بَشَرٌۭ","qpc_uthmani_hafs":"بَشَرٞ","char_type_name":"word","page_number":373,"line_number":11,"text":"بَشَرٞ","translation":{"text":"a man","language_name":"english","language_id":38},"transliteration":{"text":"basharun","language_name":"english","language_id":38}},{"id":80923,"position":5,"audio_url":"wbw/026_154_005.mp3","verse_key":"26:154","verse_id":3086,"location":"26:154:5","text_uthmani":"مِّثْلُنَا","qpc_uthmani_hafs":"مِّثۡلُنَا","char_type_name":"word","page_number":373,"line_number":11,"text":"مِّثۡلُنَا","translation":{"text":"like us","language_name":"english","language_id":38},"transliteration":{"text":"mith'lunā","language_name":"english","language_id":38}},{"id":80924,"position":6,"audio_url":"wbw/026_154_006.mp3","verse_key":"26:154","verse_id":3086,"location":"26:154:6","text_uthmani":"فَأْتِ","qpc_uthmani_hafs":"فَأۡتِ","char_type_name":"word","page_number":373,"line_number":11,"text":"فَأۡتِ","translation":{"text":"so bring","language_name":"english","language_id":38},"transliteration":{"text":"fati","language_name":"english","language_id":38}},{"id":80925,"position":7,"audio_url":"wbw/026_154_007.mp3","verse_key":"26:154","verse_id":3086,"location":"26:154:7","text_uthmani":"بِـَٔايَةٍ","qpc_uthmani_hafs":"بِـَٔايَةٍ","char_type_name":"word","page_number":373,"line_number":11,"text":"بِـَٔايَةٍ","translation":{"text":"a sign","language_name":"english","language_id":38},"transliteration":{"text":"biāyatin","language_name":"english","language_id":38}},{"id":80926,"position":8,"audio_url":"wbw/026_154_008.mp3","verse_key":"26:154","verse_id":3086,"location":"26:154:8","text_uthmani":"إِن","qpc_uthmani_hafs":"إِن","char_type_name":"word","page_number":373,"line_number":11,"text":"إِن","translation":{"text":"if","language_name":"english","language_id":38},"transliteration":{"text":"in","language_name":"english","language_id":38}},{"id":80927,"position":9,"audio_url":"wbw/026_154_009.mp3","verse_key":"26:154","verse_id":3086,"location":"26:154:9","text_uthmani":"كُنتَ","qpc_uthmani_hafs":"كُنتَ","char_type_name":"word","page_number":373,"line_number":11,"text":"كُنتَ","translation":{"text":"you","language_name":"english","language_id":38},"transliteration":{"text":"kunta","language_name":"english","language_id":38}},{"id":80928,"position":10,"audio_url":"wbw/026_154_010.mp3","verse_key":"26:154","verse_id":3086,"location":"26:154:10","text_uthmani":"مِنَ","qpc_uthmani_hafs":"مِنَ","char_type_name":"word","page_number":373,"line_number":11,"text":"مِنَ","translation":{"text":"(are) of","language_name":"english","language_id":38},"transliteration":{"text":"mina","language_name":"english","language_id":38}},{"id":80929,"position":11,"audio_url":"wbw/026_154_011.mp3","verse_key":"26:154","verse_id":3086,"location":"26:154:11","text_uthmani":"ٱلصَّـٰدِقِينَ","qpc_uthmani_hafs":"ٱلصَّٰدِقِينَ","char_type_name":"word","page_number":373,"line_number":11,"text":"ٱلصَّٰدِقِينَ","translation":{"text":"the truthful","language_name":"english","language_id":38},"transliteration":{"text":"l-ṣādiqīna","language_name":"english","language_id":38}},{"id":80930,"position":12,"audio_url":null,"verse_key":"26:154","verse_id":3086,"location":"26:154:12","text_uthmani":"١٥٤","qpc_uthmani_hafs":"١٥٤","char_type_name":"end","page_number":373,"line_number":11,"text":"١٥٤","translation":{"text":"(154)","language_name":"english","language_id":38},"transliteration":{"text":null,"language_name":"english","language_id":38}}]},{"id":3087,"verse_number":155,"verse_key":"26:155","hizb_number":38,"rub_el_hizb_number":149,"ruku_number":323,"manzil_number":5,"sajdah_number":null,"page_number":373,"juz_number":19,"words":[{"id":81119,"position":1,"audio_url":"wbw/026_155_001.mp3","verse_key":"26:155","verse_id":3087,"location":"26:155:1","text_uthmani":"قَالَ","qpc_uthmani_hafs":"قَالَ","char_type_name":"word","page_number":373,"line_number":11,"text":"قَالَ","translation":{"text":"He said","language_name":"english","language_id":38},"transliteration":{"text":"qāla","language_name":"english","language_id":38}},{"id":81120,"position":2,"audio_url":"wbw/026_155_002.mp3","verse_key":"26:155","verse_id":3087,"location":"26:155:2","text_uthmani":"هَـٰذِهِۦ","qpc_uthmani_hafs":"هَٰذِهِۦ","char_type_name":"word","page_number":373,"line_number":12,"text":"هَٰذِهِۦ","translation":{"text":"This","language_name":"english","language_id":38},"transliteration":{"text":"hādhihi","language_name":"english","language_id":38}},{"id":81121,"position":3,"audio_url":"wbw/026_155_003.mp3","verse_key":"26:155","verse_id":3087,"location":"26:155:3","text_uthmani":"نَاقَةٌۭ","qpc_uthmani_hafs":"نَاقَةٞ","char_type_name":"word","page_number":373,"line_number":12,"text":"نَاقَةٞ","translation":{"text":"(is) a she-camel","language_name":"english","language_id":38},"transliteration":{"text":"nāqatun","language_name":"english","language_id":38}},{"id":81122,"position":4,"audio_url":"wbw/026_155_004.mp3","verse_key":"26:155","verse_id":3087,"location":"26:155:4","text_uthmani":"لَّهَا","qpc_uthmani_hafs":"لَّهَا","char_type_name":"word","page_number":373,"line_number":12,"text":"لَّهَا","translation":{"text":"For her","language_name":"english","language_id":38},"transliteration":{"text":"lahā","language_name":"english","language_id":38}},{"id":81123,"position":5,"audio_url":"wbw/026_155_005.mp3","verse_key":"26:155","verse_id":3087,"location":"26:155:5","text_uthmani":"شِرْبٌۭ","qpc_uthmani_hafs":"شِرۡبٞ","char_type_name":"word","page_number":373,"line_number":12,"text":"شِرۡبٞ","translation":{"text":"(is a share of) drink","language_name":"english","language_id":38},"transliteration":{"text":"shir'bun","language_name":"english","language_id":38}},{"id":81124,"position":6,"audio_url":"wbw/026_155_006.mp3","verse_key":"26:155","verse_id":3087,"location":"26:155:6","text_uthmani":"وَلَكُمْ","qpc_uthmani_hafs":"وَلَكُمۡ","char_type_name":"word","page_number":373,"line_number":12,"text":"وَلَكُمۡ","translation":{"text":"and for you","language_name":"english","language_id":38},"transliteration":{"text":"walakum","language_name":"english","language_id":38}},{"id":81125,"position":7,"audio_url":"wbw/026_155_007.mp3","verse_key":"26:155","verse_id":3087,"location":"26:155:7","text_uthmani":"شِرْبُ","qpc_uthmani_hafs":"شِرۡبُ","char_type_name":"word","page_number":373,"line_number":12,"text":"شِرۡبُ","translation":{"text":"(is a share of) drink","language_name":"english","language_id":38},"transliteration":{"text":"shir'bu","language_name":"english","language_id":38}},{"id":81126,"position":8,"audio_url":"wbw/026_155_008.mp3","verse_key":"26:155","verse_id":3087,"location":"26:155:8","text_uthmani":"يَوْمٍۢ","qpc_uthmani_hafs":"يَوۡمٖ","char_type_name":"word","page_number":373,"line_number":12,"text":"يَوۡمٖ","translation":{"text":"(on) a day","language_name":"english","language_id":38},"transliteration":{"text":"yawmin","language_name":"english","language_id":38}},{"id":81127,"position":9,"audio_url":"wbw/026_155_009.mp3","verse_key":"26:155","verse_id":3087,"location":"26:155:9","text_uthmani":"مَّعْلُومٍۢ","qpc_uthmani_hafs":"مَّعۡلُومٖ","char_type_name":"word","page_number":373,"line_number":12,"text":"مَّعۡلُومٖ","translation":{"text":"known","language_name":"english","language_id":38},"transliteration":{"text":"maʿlūmin","language_name":"english","language_id":38}},{"id":81128,"position":10,"audio_url":null,"verse_key":"26:155","verse_id":3087,"location":"26:155:10","text_uthmani":"١٥٥","qpc_uthmani_hafs":"١٥٥","char_type_name":"end","page_number":373,"line_number":12,"text":"١٥٥","translation":{"text":"(155)","language_name":"english","language_id":38},"transliteration":{"text":null,"language_name":"english","language_id":38}}]},{"id":3088,"verse_number":156,"verse_key":"26:156","hizb_number":38,"rub_el_hizb_number":149,"ruku_number":323,"manzil_number":5,"sajdah_number":null,"page_number":373,"juz_number":19,"words":[{"id":81226,"position":1,"audio_url":"wbw/026_156_001.mp3","verse_key":"26:156","verse_id":3088,"location":"26:156:1","text_uthmani":"وَلَا","qpc_uthmani_hafs":"وَلَا","char_type_name":"word","page_number":373,"line_number":12,"text":"وَلَا","translation":{"text":"And (do) not","language_name":"english","language_id":38},"transliteration":{"text":"walā","language_name":"english","language_id":38}},{"id":81227,"position":2,"audio_url":"wbw/026_156_002.mp3","verse_key":"26:156","verse_id":3088,"location":"26:156:2","text_uthmani":"تَمَسُّوهَا","qpc_uthmani_hafs":"تَمَسُّوهَا","char_type_name":"word","page_number":373,"line_number":12,"text":"تَمَسُّوهَا","translation":{"text":"touch her","language_name":"english","language_id":38},"transliteration":{"text":"tamassūhā","language_name":"english","language_id":38}},{"id":81228,"position":3,"audio_url":"wbw/026_156_003.mp3","verse_key":"26:156","verse_id":3088,"location":"26:156:3","text_uthmani":"بِسُوٓءٍۢ","qpc_uthmani_hafs":"بِسُوٓءٖ","char_type_name":"word","page_number":373,"line_number":13,"text":"بِسُوٓءٖ","translation":{"text":"with harm","language_name":"english","language_id":38},"transliteration":{"text":"bisūin","language_name":"english","language_id":38}},{"id":81229,"position":4,"audio_url":"wbw/026_156_004.mp3","verse_key":"26:156","verse_id":3088,"location":"26:156:4","text_uthmani":"فَيَأْخُذَكُمْ","qpc_uthmani_hafs":"فَيَأۡخُذَكُمۡ","char_type_name":"word","page_number":373,"line_number":13,"text":"فَيَأۡخُذَكُمۡ","translation":{"text":"lest seize you","language_name":"english","language_id":38},"transliteration":{"text":"fayakhudhakum","language_name":"english","language_id":38}},{"id":81230,"position":5,"audio_url":"wbw/026_156_005.mp3","verse_key":"26:156","verse_id":3088,"location":"26:156:5","text_uthmani":"عَذَابُ","qpc_uthmani_hafs":"عَذَابُ","char_type_name":"word","page_number":373,"line_number":13,"text":"عَذَابُ","translation":{"text":"(the) punishment","language_name":"english","language_id":38},"transliteration":{"text":"ʿadhābu","language_name":"english","language_id":38}},{"id":81231,"position":6,"audio_url":"wbw/026_156_006.mp3","verse_key":"26:156","verse_id":3088,"location":"26:156:6","text_uthmani":"يَوْمٍ","qpc_uthmani_hafs":"يَوۡمٍ","char_type_name":"word","page_number":373,"line_number":13,"text":"يَوۡمٍ","translation":{"text":"(of) a Day","language_name":"english","language_id":38},"transliteration":{"text":"yawmin","language_name":"english","language_id":38}},{"id":81232,"position":7,"audio_url":"wbw/026_156_007.mp3","verse_key":"26:156","verse_id":3088,"location":"26:156:7","text_uthmani":"عَظِيمٍۢ","qpc_uthmani_hafs":"عَظِيمٖ","char_type_name":"word","page_number":373,"line_number":13,"text":"عَظِيمٖ","translation":{"text":"Great","language_name":"english","language_id":38},"transliteration":{"text":"ʿaẓīmin","language_name":"english","language_id":38}},{"id":81233,"position":8,"audio_url":null,"verse_key":"26:156","verse_id":3088,"location":"26:156:8","text_uthmani":"١٥٦","qpc_uthmani_hafs":"١٥٦","char_type_name":"end","page_number":373,"line_number":13,"text":"١٥٦","translation":{"text":"(156)","language_name":"english","language_id":38},"transliteration":{"text":null,"language_name":"english","language_id":38}}]},{"id":3089,"verse_number":157,"verse_key":"26:157","hizb_number":38,"rub_el_hizb_number":149,"ruku_number":323,"manzil_number":5,"sajdah_number":null,"page_number":373,"juz_number":19,"words":[{"id":81388,"position":1,"audio_url":"wbw/026_157_001.mp3","verse_key":"26:157","verse_id":3089,"location":"26:157:1","text_uthmani":"فَعَقَرُوهَا","qpc_uthmani_hafs":"فَعَقَرُوهَا","char_type_name":"word","page_number":373,"line_number":13,"text":"فَعَقَرُوهَا","translation":{"text":"But they hamstrung her","language_name":"english","language_id":38},"transliteration":{"text":"faʿaqarūhā","language_name":"english","language_id":38}},{"id":81389,"position":2,"audio_url":"wbw/026_157_002.mp3","verse_key":"26:157","verse_id":3089,"location":"26:157:2","text_uthmani":"فَأَصْبَحُوا۟","qpc_uthmani_hafs":"فَأَصۡبَحُواْ","char_type_name":"word","page_number":373,"line_number":13,"text":"فَأَصۡبَحُواْ","translation":{"text":"then they became","language_name":"english","language_id":38},"transliteration":{"text":"fa-aṣbaḥū","language_name":"english","language_id":38}},{"id":81390,"position":3,"audio_url":"wbw/026_157_003.mp3","verse_key":"26:157","verse_id":3089,"location":"26:157:3","text_uthmani":"نَـٰدِمِينَ","qpc_uthmani_hafs":"نَٰدِمِينَ","char_type_name":"word","page_number":373,"line_number":14,"text":"نَٰدِمِينَ","translation":{"text":"regretful","language_name":"english","language_id":38},"transliteration":{"text":"nādimīna","language_name":"english","language_id":38}},{"id":81391,"position":4,"audio_url":null,"verse_key":"26:157","verse_id":3089,"location":"26:157:4","text_uthmani":"١٥٧","qpc_uthmani_hafs":"١٥٧","char_type_name":"end","page_number":373,"line_number":14,"text":"١٥٧","translation":{"text":"(157)","language_name":"english","language_id":38},"transliteration":{"text":null,"language_name":"english","language_id":38}}]},{"id":3090,"verse_number":158,"verse_key":"26:158","hizb_number":38,"rub_el_hizb_number":149,"ruku_number":323,"manzil_number":5,"sajdah_number":null,"page_number":373,"juz_number":19,"words":[{"id":81516,"position":1,"audio_url":"wbw/026_158_001.mp3","verse_key":"26:158","verse_id":3090,"location":"26:158:1","text_uthmani":"فَأَخَذَهُمُ","qpc_uthmani_hafs":"فَأَخَذَهُمُ","char_type_name":"word","page_number":373,"line_number":14,"text":"فَأَخَذَهُمُ","translation":{"text":"So seized them","language_name":"english","language_id":38},"transliteration":{"text":"fa-akhadhahumu","language_name":"english","language_id":38}},{"id":81517,"position":2,"audio_url":"wbw/026_158_002.mp3","verse_key":"26:158","verse_id":3090,"location":"26:158:2","text_uthmani":"ٱلْعَذَابُ ۗ","qpc_uthmani_hafs":"ٱلۡعَذَابُۚ","char_type_name":"word","page_number":373,"line_number":14,"text":"ٱلۡعَذَابُۚ","translation":{"text":"the punishment","language_name":"english","language_id":38},"transliteration":{"text":"l-ʿadhābu","language_name":"english","language_id":38}},{"id":81519,"position":3,"audio_url":"wbw/026_158_004.mp3","verse_key":"26:158","verse_id":3090,"location":"26:158:3","text_uthmani":"إِنَّ","qpc_uthmani_hafs":"إِنَّ","char_type_name":"word","page_number":373,"line_number":14,"text":"إِنَّ","translation":{"text":"Indeed","language_name":"english","language_id":38},"transliteration":{"text":"inna","language_name":"english","language_id":38}},{"id":81520,"position":4,"audio_url":"wbw/026_158_005.mp3","verse_key":"26:158","verse_id":3090,"location":"26:158:4","text_uthmani":"فِى","qpc_uthmani_hafs":"فِي","char_type_name":"word","page_number":373,"line_number":14,"text":"فِي","translation":{"text":"in","language_name":"english","language_id":38},"transliteration":{"text":"fī","language_name":"english","language_id":38}},{"id":81521,"position":5,"audio_url":"wbw/026_158_006.mp3","verse_key":"26:158","verse_id":3090,"location":"26:158:5","text_uthmani":"ذَٰلِكَ","qpc_uthmani_hafs":"ذَٰلِكَ","char_type_name":"word","page_number":373,"line_number":14,"text":"ذَٰلِكَ","translation":{"text":"that","language_name":"english","language_id":38},"transliteration":{"text":"dhālika","language_name":"english","language_id":38}},{"id":81522,"position":6,"audio_url":"wbw/026_158_007.mp3","verse_key":"26:158","verse_id":3090,"location":"26:158:6","text_uthmani":"لَـَٔايَةًۭ ۖ","qpc_uthmani_hafs":"لَأٓيَةٗۖ","char_type_name":"word","page_number":373,"line_number":14,"text":"لَأٓيَةٗۖ","translation":{"text":"surely is a sign","language_name":"english","language_id":38},"transliteration":{"text":"laāyatan","language_name":"english","language_id":38}},{"id":81524,"position":7,"audio_url":"wbw/026_158_009.mp3","verse_key":"26:158","verse_id":3090,"location":"26:158:7","text_uthmani":"وَمَا","qpc_uthmani_hafs":"وَمَا","char_type_name":"word","page_number":373,"line_number":14,"text":"وَمَا","translation":{"text":"but not","language_name":"english","language_id":38},"transliteration":{"text":"wamā","language_name":"english","language_id":38}},{"id":81525,"position":8,"audio_url":"wbw/026_158_010.mp3","verse_key":"26:158","verse_id":3090,"location":"26:158:8","text_uthmani":"كَانَ","qpc_uthmani_hafs":"كَانَ","char_type_name":"word","page_number":373,"line_number":14,"text":"كَانَ","translation":{"text":"are","language_name":"english","language_id":38},"transliteration":{"text":"kāna","language_name":"english","language_id":38}},{"id":81526,"position":9,"audio_url":"wbw/026_158_011.mp3","verse_key":"26:158","verse_id":3090,"location":"26:158:9","text_uthmani":"أَكْثَرُهُم","qpc_uthmani_hafs":"أَكۡثَرُهُم","char_type_name":"word","page_number":373,"line_number":15,"text":"أَكۡثَرُهُم","translation":{"text":"most of them","language_name":"english","language_id":38},"transliteration":{"text":"aktharuhum","language_name":"english","language_id":38}},{"id":81527,"position":10,"audio_url":"wbw/026_158_012.mp3","verse_key":"26:158","verse_id":3090,"location":"26:158:10","text_uthmani":"مُّؤْمِنِينَ","qpc_uthmani_hafs":"مُّؤۡمِنِينَ","char_type_name":"word","page_number":373,"line_number":15,"text":"مُّؤۡمِنِينَ","translation":{"text":"believers","language_name":"english","language_id":38},"transliteration":{"text":"mu'minīna","language_name":"english","language_id":38}},{"id":81528,"position":11,"audio_url":null,"verse_key":"26:158","verse_id":3090,"location":"26:158:11","text_uthmani":"١٥٨","qpc_uthmani_hafs":"١٥٨","char_type_name":"end","page_number":373,"line_number":15,"text":"١٥٨","translation":{"text":"(158)","language_name":"english","language_id":38},"transliteration":{"text":null,"language_name":"english","language_id":38}}]},{"id":3091,"verse_number":159,"verse_key":"26:159","hizb_number":38,"rub_el_hizb_number":149,"ruku_number":323,"manzil_number":5,"sajdah_number":null,"page_number":373,"juz_number":19,"words":[{"id":81679,"position":1,"audio_url":"wbw/026_159_001.mp3","verse_key":"26:159","verse_id":3091,"location":"26:159:1","text_uthmani":"وَإِنَّ","qpc_uthmani_hafs":"وَإِنَّ","char_type_name":"word","page_number":373,"line_number":15,"text":"وَإِنَّ","translation":{"text":"And indeed","language_name":"english","language_id":38},"transliteration":{"text":"wa-inna","language_name":"english","language_id":38}},{"id":81680,"position":2,"audio_url":"wbw/026_159_002.mp3","verse_key":"26:159","verse_id":3091,"location":"26:159:2","text_uthmani":"رَبَّكَ","qpc_uthmani_hafs":"رَبَّكَ","char_type_name":"word","page_number":373,"line_number":15,"text":"رَبَّكَ","translation":{"text":"your Lord","language_name":"english","language_id":38},"transliteration":{"text":"rabbaka","language_name":"english","language_id":38}},{"id":81681,"position":3,"audio_url":"wbw/026_159_003.mp3","verse_key":"26:159","verse_id":3091,"location":"26:159:3","text_uthmani":"لَهُوَ","qpc_uthmani_hafs":"لَهُوَ","char_type_name":"word","page_number":373,"line_number":15,"text":"لَهُوَ","translation":{"text":"surely He","language_name":"english","language_id":38},"transliteration":{"text":"lahuwa","language_name":"english","language_id":38}},{"id":81682,"position":4,"audio_url":"wbw/026_159_004.mp3","verse_key":"26:159","verse_id":3091,"location":"26:159:4","text_uthmani":"ٱلْعَزِيزُ","qpc_uthmani_hafs":"ٱلۡعَزِيزُ","char_type_name":"word","page_number":373,"line_number":15,"text":"ٱلۡعَزِيزُ","translation":{"text":"(is) the All-Mighty","language_name":"english","language_id":38},"transliteration":{"text":"l-ʿazīzu","language_name":"english","language_id":38}},{"id":81683,"position":5,"audio_url":"wbw/026_159_005.mp3","verse_key":"26:159","verse_id":3091,"location":"26:159:5","text_uthmani":"ٱلرَّحِيمُ","qpc_uthmani_hafs":"ٱلرَّحِيمُ","char_type_name":"word","page_number":373,"line_number":15,"text":"ٱلرَّحِيمُ","translation":{"text":"the Most Merciful","language_name":"english","language_id":38},"transliteration":{"text":"l-raḥīmu","language_name":"english","language_id":38}},{"id":81684,"position":6,"audio_url":null,"verse_key":"26:159","verse_id":3091,"location":"26:159:6","text_uthmani":"١٥٩","qpc_uthmani_hafs":"١٥٩","char_type_name":"end","page_number":373,"line_number":15,"text":"١٥٩","translation":{"text":"(159)","language_name":"english","language_id":38},"transliteration":{"text":null,"language_name":"english","language_id":38}}]},{"id":3092,"verse_number":160,"verse_key":"26:160","hizb_number":38,"rub_el_hizb_number":149,"ruku_number":324,"manzil_number":5,"sajdah_number":null,"page_number":374,"juz_number":19,"words":[{"id":81848,"position":1,"audio_url":"wbw/026_160_001.mp3","verse_key":"26:160","verse_id":3092,"location":"26:160:1","text_uthmani":"كَذَّبَتْ","qpc_uthmani_hafs":"كَذَّبَتۡ","char_type_name":"word","page_number":374,"line_number":1,"text":"كَذَّبَتۡ","translation":{"text":"Denied","language_name":"english","language_id":38},"transliteration":{"text":"kadhabat","language_name":"english","language_id":38}},{"id":81849,"position":2,"audio_url":"wbw/026_160_002.mp3","verse_key":"26:160","verse_id":3092,"location":"26:160:2","text_uthmani":"قَوْمُ","qpc_uthmani_hafs":"قَوۡمُ","char_type_name":"word","page_number":374,"line_number":1,"text":"قَوۡمُ","translation":{"text":"(the) people","language_name":"english","language_id":38},"transliteration":{"text":"qawmu","language_name":"english","language_id":38}},{"id":81850,"position":3,"audio_url":"wbw/026_160_003.mp3","verse_key":"26:160","verse_id":3092,"location":"26:160:3","text_uthmani":"لُوطٍ","qpc_uthmani_hafs":"لُوطٍ","char_type_name":"word","page_number":374,"line_number":1,"text":"لُوطٍ","translation":{"text":"(of) Lut","language_name":"english","language_id":38},"transliteration":{"text":"lūṭin","language_name":"english","language_id":38}},{"id":81851,"position":4,"audio_url":"wbw/026_160_004.mp3","verse_key":"26:160","verse_id":3092,"location":"26:160:4","text_uthmani":"ٱلْمُرْسَلِينَ","qpc_uthmani_hafs":"ٱلۡمُرۡسَلِينَ","char_type_name":"word","page_number":374,"line_number":1,"text":"ٱلۡمُرۡسَلِينَ","translation":{"text":"the Messengers","language_name":"english","language_id":38},"transliteration":{"text":"l-mur'salīna","language_name":"english","language_id":38}},{"id":81852,"position":5,"audio_url":null,"verse_key":"26:160","verse_id":3092,"location":"26:160:5","text_uthmani":"١٦٠","qpc_uthmani_hafs":"١٦٠","char_type_name":"end","page_number":374,"line_number":1,"text":"١٦٠","translation":{"text":"(160)","language_name":"english","language_id":38},"transliteration":{"text":null,"language_name":"english","language_id":38}}]}],"pagination":{"per_page":10,"current_page":16,"next_page":17,"total_pages":23,"total_records":227}}
