{"Verses":[{"Id":1,"verse_number":1,"verse_key":"97:1","Words":[{"Id":169,"Position":1,"text_uthmani":"إِنَّآ","qpc_uthmani_hafs":"إِنَّآ","Text":"إِنَّآ","Translation":{"Text":"নিশ্চয়ই","language_name":"bengali","language_id":20}},{"Id":170,"Position":2,"text_uthmani":"أَنزَلْنَـٰهُ","qpc_uthmani_hafs":"أَنزَلۡنَٰهُ","Text":"أَنزَلۡنَٰهُ","Translation":{"Text":"তা আমরা অবতীর্ণ করেছি","language_name":"bengali","language_id":20}},{"Id":171,"Position":3,"text_uthmani":"فِى","qpc_uthmani_hafs":"فِي","Text":"فِي","Translation":{"Text":"মধ্যে","language_name":"bengali","language_id":20}},{"Id":172,"Position":4,"text_uthmani":"لَيْلَةِ","qpc_uthmani_hafs":"لَيۡلَةِ","Text":"لَيۡلَةِ","Translation":{"Text":"রাতের","language_name":"bengali","language_id":20}},{"Id":173,"Position":5,"text_uthmani":"ٱلْقَدْرِ","qpc_uthmani_hafs":"ٱلۡقَدۡرِ","Text":"ٱلۡقَدۡرِ","Translation":{"Text":"কদরের/ মহিমার","language_name":"bengali","language_id":20}},{"Id":174,"Position":6,"text_uthmani":"١","qpc_uthmani_hafs":"١","Text":"١","Translation":{"Text":"(১)","language_name":"bengali","language_id":20}}]},{"Id":2,"verse_number":2,"verse_key":"97:2","Words":[{"Id":1789,"Position":1,"text_uthmani":"وَمَآ","qpc_uthmani_hafs":"وَمَآ","Text":"وَمَآ","Translation":{"Text":"এবং কিসে","language_name":"bengali","language_id":20}},{"Id":1790,"Position":2,"text_uthmani":"أَدْرَىٰكَ","qpc_uthmani_hafs":"أَدۡرَىٰكَ","Text":"أَدۡرَىٰكَ","Translation":{"Text":"তোমাকে জানাবে","language_name":"bengali","language_id":20}},{"Id":1791,"Position":3,"text_uthmani":"مَا","qpc_uthmani_hafs":"مَا","Text":"مَا","Translation":{"Text":"কি সেই","language_name":"bengali","language_id":20}},{"Id":1792,"Position":4,"text_uthmani":"لَيْلَةُ","qpc_uthmani_hafs":"لَيۡلَةُ","Text":"لَيۡلَةُ","Translation":{"Text":"রাত","language_name":"bengali","language_id":20}},{"Id":1793,"Position":5,"text_uthmani":"ٱلْقَدْرِ","qpc_uthmani_hafs":"ٱلۡقَدۡرِ","Text":"ٱلۡقَدۡرِ","Translation":{"Text":"কদরের","language_name":"bengali","language_id":20}},{"Id":1794,"Position":6,"text_uthmani":"٢","qpc_uthmani_hafs":"٢","Text":"٢","Translation":{"Text":"(২)","language_name":"bengali","language_id":20}}]},{"Id":3,"verse_number":3,"verse_key":"97:3","Words":[{"Id":2900,"Position":1,"text_uthmani":"لَيْلَةُ","qpc_uthmani_hafs":"لَيۡلَةُ","Text":"لَيۡلَةُ","Translation":{"Text":"রাত","language_name":"bengali","language_id":20}},{"Id":2901,"Position":2,"text_uthmani":"ٱلْقَدْرِ","qpc_uthmani_hafs":"ٱلۡقَدۡرِ","Text":"ٱلۡقَدۡرِ","Translation":{"Text":"কদরের","language_name":"bengali","language_id":20}},{"Id":2902,"Position":3,"text_uthmani":"خَيْرٌۭ","qpc_uthmani_hafs":"خَيۡرٞ","Text":"خَيۡرٞ","Translation":{"Text":"শ্রেষ্ঠ","language_name":"bengali","language_id":20}},{"Id":2903,"Position":4,"text_uthmani":"مِّنْ","qpc_uthmani_hafs":"مِّنۡ","Text":"مِّنۡ","Translation":{"Text":"হতেও","language_name":"bengali","language_id":20}},{"Id":2904,"Position":5,"text_uthmani":"أَلْفِ","qpc_uthmani_hafs":"أَلۡفِ","Text":"أَلۡفِ","Translation":{"Text":"হাজার","language_name":"bengali","language_id":20}},{"Id":2905,"Position":6,"text_uthmani":"شَهْرٍۢ","qpc_uthmani_hafs":"شَهۡرٖ","Text":"شَهۡرٖ","Translation":{"Text":"মাস","language_name":"bengali","language_id":20}},{"Id":2906,"Position":7,"text_uthmani":"٣","qpc_uthmani_hafs":"٣","Text":"٣","Translation":{"Text":"(৩)","language_name":"bengali","language_id":20}}]},{"Id":4,"verse_number":4,"verse_key":"97:4","Words":[{"Id":4399,"Position":1,"text_uthmani":"تَنَزَّلُ","qpc_uthmani_hafs":"تَنَزَّلُ","Text":"تَنَزَّلُ","Translation":{"Text":"অবতীর্ণ হয়","language_name":"bengali","language_id":20}},{"Id":4400,"Position":2,"text_uthmani":"ٱلْمَلَـٰٓئِكَةُ","qpc_uthmani_hafs":"ٱلۡمَلَٰٓئِكَةُ","Text":"ٱلۡمَلَٰٓئِكَةُ","Translation":{"Text":"ফেরেশতারা","language_name":"bengali","language_id":20}},{"Id":4401,"Position":3,"text_uthmani":"وَٱلرُّوحُ","qpc_uthmani_hafs":"وَٱلرُّوحُ","Text":"وَٱلرُّوحُ","Translation":{"Text":"এবং রূহ (জিব্রাঈল)","language_name":"bengali","language_id":20}},{"Id":4402,"Position":4,"text_uthmani":"فِيهَا","qpc_uthmani_hafs":"فِيهَا","Text":"فِيهَا","Translation":{"Text":"তার মধ্যে","language_name":"bengali","language_id":20}},{"Id":4403,"Position":5,"text_uthmani":"بِإِذْنِ","qpc_uthmani_hafs":"بِإِذۡنِ","Text":"بِإِذۡنِ","Translation":{"Text":"অনুমতিক্রমে","language_name":"bengali","language_id":20}},{"Id":4404,"Position":6,"text_uthmani":"رَبِّهِم","qpc_uthmani_hafs":"رَبِّهِم","Text":"رَبِّهِم","Translation":{"Text":"তাদের রবের","language_name":"bengali","language_id":20}},{"Id":4405,"Position":7,"text_uthmani":"مِّن","qpc_uthmani_hafs":"مِّن","Text":"مِّن","Translation":{"Text":"প্রত্যেক","language_name":"bengali","language_id":20}},{"Id":4406,"Position":8,"text_uthmani":"كُلِّ","qpc_uthmani_hafs":"كُلِّ","Text":"كُلِّ","Translation":{"Text":"সব","language_name":"bengali","language_id":20}},{"Id":4407,"Position":9,"text_uthmani":"أَمْرٍۢ","qpc_uthmani_hafs":"أَمۡرٖ","Text":"أَمۡرٖ","Translation":{"Text":"কাজে","language_name":"bengali","language_id":20}},{"Id":4408,"Position":10,"text_uthmani":"٤","qpc_uthmani_hafs":"٤","Text":"٤","Translation":{"Text":"(৪)","language_name":"bengali","language_id":20}}]},{"Id":5,"verse_number":5,"verse_key":"97:5","Words":[{"Id":4984,"Position":1,"text_uthmani":"سَلَـٰمٌ","qpc_uthmani_hafs":"سَلَٰمٌ","Text":"سَلَٰمٌ","Translation":{"Text":"শান্তির","language_name":"bengali","language_id":20}},{"Id":4985,"Position":2,"text_uthmani":"هِىَ","qpc_uthmani_hafs":"هِيَ","Text":"هِيَ","Translation":{"Text":"সেই (রাত)","language_name":"bengali","language_id":20}},{"Id":4986,"Position":3,"text_uthmani":"حَتَّىٰ","qpc_uthmani_hafs":"حَتَّىٰ","Text":"حَتَّىٰ","Translation":{"Text":"পর্যন্ত","language_name":"bengali","language_id":20}},{"Id":4987,"Position":4,"text_uthmani":"مَطْلَعِ","qpc_uthmani_hafs":"مَطۡلَعِ","Text":"مَطۡلَعِ","Translation":{"Text":"উদয়","language_name":"bengali","language_id":20}},{"Id":4988,"Position":5,"text_uthmani":"ٱلْفَجْرِ","qpc_uthmani_hafs":"ٱلۡفَجۡرِ","Text":"ٱلۡفَجۡرِ","Translation":{"Text":"ঊষার","language_name":"bengali","language_id":20}},{"Id":4989,"Position":6,"text_uthmani":"٥","qpc_uthmani_hafs":"٥","Text":"٥","Translation":{"Text":"(৫)","language_name":"bengali","language_id":20}}]}]}